{
  "GuideData": {


     "AdsController": [
      {
        "NetworkAds": "facebook",
        "AdMobId": "pub-9292747925101000",

        "BannerAdmob": "ca-app-pub-9292747925101000/1074647052",
        "InterstitialAdmob": "ca-app-pub-9292747925101000/8216261162",
        "NativeAdmob": "ca-app-pub-9292747925101000/7424772292",

        "BannerFacebook": "660870764851588_701632484108749",
        "InterstitialFacebook": "660870764851588_701632364108761",
        "NativeFacebook": "660870764851588_701632217442109"

      }
    ],

    "items": [
      {
        "title": "WHAT PARENTS NEED TO KNOW",
        "image": "https://1.bp.blogspot.com/-MG1DcbGWJSo/X7TPoBs0goI/AAAAAAAAA_8/CLx4C6YKLRcVTeIsxGz34TEaUymKdxl-ACNcBGAsYHQ/s1200/111.png"
      },
      {
        "title": "WHAT'S IT ABOUT?",
        "image": "https://1.bp.blogspot.com/-MG1DcbGWJSo/X7TPoBs0goI/AAAAAAAAA_8/CLx4C6YKLRcVTeIsxGz34TEaUymKdxl-ACNcBGAsYHQ/s1200/111.png"
      },
      {
        "title": "IS IT ANY GOOD?",
        "image": "https://1.bp.blogspot.com/-MG1DcbGWJSo/X7TPoBs0goI/AAAAAAAAA_8/CLx4C6YKLRcVTeIsxGz34TEaUymKdxl-ACNcBGAsYHQ/s1200/111.png"
      },
      {
        "title": "TALK TO YOUR KIDS ABOUT ...",
        "image": "https://1.bp.blogspot.com/-MG1DcbGWJSo/X7TPoBs0goI/AAAAAAAAA_8/CLx4C6YKLRcVTeIsxGz34TEaUymKdxl-ACNcBGAsYHQ/s1200/111.png"
      },
      {
        "title": "APP DETAILS",
        "image": "https://1.bp.blogspot.com/-MG1DcbGWJSo/X7TPoBs0goI/AAAAAAAAA_8/CLx4C6YKLRcVTeIsxGz34TEaUymKdxl-ACNcBGAsYHQ/s1200/111.png"
      }
    ],

    "content1": [
      {
        "ordered": "image_text",
        "color": "#f56342",
        "style": "blood",
        "gravity": "left",
        "left": "10",
        "text_size": "25",
        "isLink": "false",
        "link_title": "",
        "setLink": "",
        "image_link": "",
        "text": "WHAT PARENTS NEED TO KNOW",
        "isNative": "false"
      },
      {
        "ordered": "image_text",
        "color": "#FFFFFF",
        "style": "blood",
        "gravity": "left",
        "left": "10",
        "text_size": "20",
        "isLink": "false",
        "link_title": "",
        "setLink": "",
        "image_link": "",
        "text": "Parents need to know that Toca Life World: Build Stories combines all the apps in the Toca Life series in one place. The free download comes with eight locations and 39 characters already installed. There's a large variety of in-app purchases -- ranging in price from $.99 to $13.99 -- to add more locations and characters, and the shopping cart icon is prominently displayed at all times. If you've already purchased other Toca Life apps, you can import them into Toca Life World: Build Stories for free. As with all the apps in the series, play is open-ended and involves kids moving characters and objects around different locations. Some areas have a Record option that allows kids to record their voice as they move things around and narrate a story; for that option, the app asks for permission to access your device's microphone. Parents can turn off the background music, Toca News, Toca Mix, parents' information, the video recording option, and access to shopping for in-app purchases by finding Toca Life: World in their device's settings menu. There's a bit of potty humor: Characters sit (clothed) on a toilet, make poop and fart noises, and flush the toilet. There's also poop in a litter box. Read the developer's privacy policy for details on how your (or your kids') information is collected, used, and shared and any choices you may have in the matter, and note that privacy policies and terms of service frequently change.\n\n",
     	"isNative": "true"
      }

    ],

    "content2":
	[
      {
        "ordered": "image_text",
        "color": "#f56342",
        "style": "blood",
        "gravity": "left",
        "left": "10",
        "text_size": "25",
        "isLink": "false",
        "link_title": "",
        "setLink": "",
        "image_link": "",
        "text": "What’s New on GHD Live Sports",
        "isNative": "false"
      },
      {
        "ordered": "image_text",
        "color": "#FFFFFF",
        "style": "blood",
        "gravity": "left",
        "left": "10",
        "text_size": "20",
        "isLink": "false",
        "link_title": "",
        "setLink": "",
        "image_link": "",
        "text" : "Access all the Toca Life scenes in one TOCA LIFE WORLD: BUILD STORIES. Tap on any location -- post office, theater, or barbershop, for example -- to enter. Once in, add characters, change their clothes, and interact with objects, and then visit another location. Kids can also create their own characters and build their own buildings. Some locations allow kids to record their voice and movements on the screen. Buy more locations and characters or add Toca Life apps you've already purchased directly through Toca Life World: Build Stories. Tap the Toca Life Mix icon on the home screen to watch short animations featuring Toca Life characters and scenes.\n\n",
        "isNative": "true"
      }

    ],



"content3":
	[
      {
        "ordered": "image_text",
        "color": "#f56342",
        "style": "blood",
        "gravity": "left",
        "left": "10",
        "text_size": "25",
        "isLink": "false",
        "link_title": "",
        "setLink": "",
        "image_link": "",
        "text": "Integrated Functions in GHD Sports",
        "isNative": "false"
      },
      {
        "ordered": "image_text",
        "color": "#FFFFFF",
        "style": "blood",
        "gravity": "left",
        "left": "10",
        "text_size": "20",
        "isLink": "false",
        "link_title": "",
        "setLink": "",
        "image_link": "",
        "text" : "This seamless collection of locations, objects, and characters for open-ended imaginative play is limited mostly by how much money you want to spend. Toca Life fans will love the opportunity to collect all their worlds in one place. It's easy now to pop into the stable, go on vacation, visit the hairdresser, and stop by the office. There's opportunity here to create a huge, interconnected world -- that is, if you want to pay for it. The free download includes quite a bit of content. And those who've already bought apps in the Toca Life series have even more of a head start. But even so, growing this world requires a bit of an investment, which could make Toca Life World: Build Stories feel like a push to buy, buy, buy. It's important to note that the developer included a way to turn off the shopping icon, which gives parents a great option for avoiding this pitfall. And though it looks great to keep adding to the world, there's actually a good deal of repetition across locations. Sure, there's different scenery and some different objects, but the essence of what's available in the school isn't all that different than what's available in the city, for example. The Toca Life Mix animated stories give kids some inspiration for creating storylines and help support Toca Life World: Build Stories' storytelling potential. The build-your-own sections give kids lots of autonomy to create and take the lead in their play, but also present another area where kids can pay real money to buy more options. Toca Life World: Build Stories shines as a largely flexible platform for imaginative play. It's up to families to decide if this digital space provides as rich an opportunity for pretend play, imagination, and role play as off-screen forms of this most traditional type of play do -- or if they both have a place in their kids' lives.\n\n",
        "isNative": "true"
      }

    ],




"content4":
	[
      {
        "ordered": "image_text",
        "color": "#f56342",
        "style": "blood",
        "gravity": "left",
        "left": "10",
        "text_size": "25",
        "isLink": "false",
        "link_title": "",
        "setLink": "",
        "image_link": "",
        "text": "Download GHD SPORTS For Android Updated Version",
        "isNative": "false"
      },
      {
        "ordered": "image_text",
        "color": "#FFFFFF",
        "style": "blood",
        "gravity": "left",
        "left": "10",
        "text_size": "20",
        "isLink": "false",
        "link_title": "",
        "setLink": "",
        "image_link": "",
        "text" : "Families can talk about the narratives kids create in Toca Life World: Build Stories. Ask questions about who different characters represent, what they're doing, and why.\n\nEncourage off-screen pretend play with tea sets, dolls, stuffed animals, action figures, cardboard boxes, and more.\n\nDiscuss storytelling. If your kid wants to use the app to tell stories, encourage him or her to have a beginning, a middle, and an end and to use the recording feature in the app.",
        "isNative": "true"
      }

    ],




"content5":
	[
      {
        "ordered": "image_text",
        "color": "#f56342",
        "style": "blood",
        "gravity": "left",
        "left": "10",
        "text_size": "25",
        "isLink": "false",
        "link_title": "",
        "setLink": "",
        "image_link": "",
        "text": "GHD SPORTS LOCKDOWN UPDATE:",
        "isNative": "false"
      },
      {
        "ordered": "image_text",
        "color": "#FFFFFF",
        "style": "blood",
        "gravity": "left",
        "left": "10",
        "text_size": "20",
        "isLink": "false",
        "link_title": "",
        "setLink": "",
        "image_link": "",
        "text" : "Devices: iPhone, iPod Touch, iPad, Android, Kindle Fire\nSubjects: Language & Reading: storytelling\nSkills: Creativity: imagination\nPrice: Free to try\nPricing structure: Free to try (additional content available through in-app purchases; prices range from $.99 and up)\nRelease date: September 16, 2020\nCategory: Education\nSize: 774.70 MB\nPublisher: Toca Boca\nVersion: 1.25.1\nMinimum software requirements: iOS 10.0 or later; Android 4.4 and up\nLast updated: October 8, 2020",
        "isNative": "true"
      },

    ]
  }
}
